<?xml version="1.0" encoding="utf-8"?>
<!DOCTYPE hibernate-mapping PUBLIC "-//Hibernate/Hibernate Mapping DTD 3.0//EN"
"http://hibernate.sourceforge.net/hibernate-mapping-3.0.dtd">
<!-- 
    Mapping file autogenerated by MyEclipse Persistence Tools
-->
<hibernate-mapping>
    <class name="com.xl.repair.Repair" table="repair">
        <id name="id" type="java.lang.Integer">
            <column name="id" />
            <generator class="native" />
        </id>
        <property name="deviceId" type="java.lang.String">
            <column name="deviceId" />
        </property>
        <property name="repairPeople" type="java.lang.String">
            <column name="repairPeople" />
        </property>
        <property name="repairDate" type="java.lang.String">
            <column name="repairDate" />
        </property>
        <property name="repairPrice" type="java.lang.String">
            <column name="repairPrice" />
        </property>
    </class>
</hibernate-mapping>
